patata/__init__.py
patata/my_module.py
patatas-0.1.1.dist-info/METADATA
patatas-0.1.1.dist-info/WHEEL
patatas-0.1.1.dist-info/top_level.txt
patatas-0.1.1.dist-info/RECORD
