Metadata-Version: 2.1
Name: patatas
Version: 0.1.1
Summary: A powerful package for K-NN regression, data preprocessing, and analysis for Data Science
Home-page: https://github.com/PatataTeam/patata-poderosa
Author: Patata Team
Author-email: demstalfer@gmail.com
License: UNKNOWN
Keywords: data preprocessing knn regression analysis data science scikit-learn pandas
Platform: UNKNOWN
Classifier: Development Status :: 3 - Alpha
Classifier: Intended Audience :: Developers
Classifier: Intended Audience :: Science/Research
Classifier: License :: OSI Approved :: MIT License
Classifier: Programming Language :: Python :: 3
Classifier: Programming Language :: Python :: 3.6
Classifier: Programming Language :: Python :: 3.7
Classifier: Programming Language :: Python :: 3.8
Classifier: Programming Language :: Python :: 3.9
Classifier: Programming Language :: Python :: 3.10
Classifier: Programming Language :: Python :: 3.11
Requires-Dist: scikit-learn
Requires-Dist: pandas
Requires-Dist: numpy
Requires-Dist: matplotlib
Requires-Dist: seaborn
